tap_postgres/__init__.py
tap_postgres/db.py
tap_postgres/discovery_utils.py
tap_postgres/stream_utils.py
tap_postgres/sync_strategies/__init__.py
tap_postgres/sync_strategies/common.py
tap_postgres/sync_strategies/full_table.py
tap_postgres/sync_strategies/incremental.py
tap_postgres/sync_strategies/logical_replication.py
oc_pipelinewise_tap_postgres-2.1.1.dist-info/LICENSE
oc_pipelinewise_tap_postgres-2.1.1.dist-info/METADATA
oc_pipelinewise_tap_postgres-2.1.1.dist-info/WHEEL
oc_pipelinewise_tap_postgres-2.1.1.dist-info/entry_points.txt
oc_pipelinewise_tap_postgres-2.1.1.dist-info/top_level.txt
oc_pipelinewise_tap_postgres-2.1.1.dist-info/RECORD
