Metadata-Version: 2.1
Name: oc-pipelinewise-tap-postgres
Version: 2.1.1
Summary: Singer.io tap for extracting data from PostgresSQL - PipelineWise compatible
Home-page: https://github.com/OpenClassrooms/pipelinewise-tap-postgres
Author: Wise
Classifier: License :: OSI Approved :: GNU Affero General Public License v3
Classifier: Programming Language :: Python :: 3 :: Only
Requires-Python: >=3.7
License-File: LICENSE
Requires-Dist: pipelinewise-singer-python (==1.*)
Requires-Dist: psycopg2-binary (==2.9.6)
Requires-Dist: strict-rfc3339 (==0.7)
Provides-Extra: test
Requires-Dist: pytest (==7.2.2) ; extra == 'test'
Requires-Dist: pylint (==2.12.*) ; extra == 'test'
Requires-Dist: pytest-cov (==4.0.0) ; extra == 'test'
